pymander
