Metadata-Version: 1.1
Name: pymander
Version: 0.2.2
Summary: An interactive console application library for Python
Home-page: https://github.com/altvod/pymander
Author: Grigory Statsenko
Author-email: UNKNOWN
License: MIT
Keywords: interactive shell argparse command console
Platform: UNKNOWN
Classifier: Development Status :: 3 - Alpha
Classifier: Intended Audience :: Developers
Classifier: Topic :: Software Development :: Libraries :: Python Modules
Classifier: License :: OSI Approved :: MIT License
Classifier: Programming Language :: Python :: 3 :: Only
Classifier: Programming Language :: Python :: 3
Classifier: Programming Language :: Python :: 3.4
Classifier: Programming Language :: Python :: 3.5
